pypulse/__init__.py
pypulse/archive.py
pypulse/calibrator.py
pypulse/dmx.py
pypulse/dynamicspectrum.py
pypulse/functionfit.py
pypulse/par.py
pypulse/rfimitigator.py
pypulse/singlepulse.py
pypulse/tim.py
pypulse/utils.py
PyPulse-0.1.1.dist-info/AUTHORS.md
PyPulse-0.1.1.dist-info/LICENSE.md
PyPulse-0.1.1.dist-info/METADATA
PyPulse-0.1.1.dist-info/WHEEL
PyPulse-0.1.1.dist-info/top_level.txt
PyPulse-0.1.1.dist-info/RECORD
