Metadata-Version: 2.1
Name: PyPulse
Version: 0.1.1
Summary: A python package for handling and analyzing PSRFITS files.
Home-page: https://github.com/mtlam/PyPulse
Author: Michael Lam
Author-email: michael.lam@nanograv.org
License: BSD-3
Download-URL: https://github.com/mtlam/PyPulse/archive/v0.1.1.tar.gz
Platform: UNKNOWN
Classifier: Development Status :: 3 - Alpha
Classifier: Intended Audience :: Developers
Classifier: Intended Audience :: Science/Research
Classifier: License :: OSI Approved :: BSD License
Classifier: Operating System :: OS Independent
Classifier: Programming Language :: Python
License-File: LICENSE.md
License-File: AUTHORS.md
Requires-Dist: numpy
Requires-Dist: scipy
Requires-Dist: matplotlib
Requires-Dist: astropy
